hprocess/__init__.py
hprocess/update.py
hprocess/data/core.py
hprocess/data/function.py
hprocess/data/moduledep.py
hprocess/data/peb.py
hprocess/data/version.py
hprocess/data/__pycache__/core.cpython-311.pyc
hprocess/data/__pycache__/function.cpython-311.pyc
hprocess-1.0.2.dist-info/licenses/LICENSE.txt
hprocess-1.0.2.dist-info/METADATA
hprocess-1.0.2.dist-info/WHEEL
hprocess-1.0.2.dist-info/top_level.txt
hprocess-1.0.2.dist-info/RECORD
