Metadata-Version: 2.4
Name: hprocess
Version: 1.0.2
Summary: Process management and monitoring library
Author: huang yi yi
Author-email: 363766687@qq.com
License: MIT
Requires-Python: >=3.7
License-File: LICENSE.txt
Requires-Dist: psutil
Dynamic: author
Dynamic: author-email
Dynamic: description
Dynamic: description-content-type
Dynamic: license
Dynamic: license-file
Dynamic: requires-dist
Dynamic: requires-python
Dynamic: summary
